pynmea2/__init__.py
pynmea2/_version.py
pynmea2/nmea.py
pynmea2/nmea_file.py
pynmea2/nmea_utils.py
pynmea2/seatalk_utils.py
pynmea2/stream.py
pynmea2/types/__init__.py
pynmea2/types/talker.py
pynmea2/types/proprietary/__init__.py
pynmea2/types/proprietary/ash.py
pynmea2/types/proprietary/grm.py
pynmea2/types/proprietary/kwd.py
pynmea2/types/proprietary/mgn.py
pynmea2/types/proprietary/nor.py
pynmea2/types/proprietary/rdi.py
pynmea2/types/proprietary/srf.py
pynmea2/types/proprietary/sxn.py
pynmea2/types/proprietary/tnl.py
pynmea2/types/proprietary/ubx.py
pynmea2/types/proprietary/vtx.py
pynmea2-1.19.0.dist-info/LICENSE
pynmea2-1.19.0.dist-info/METADATA
pynmea2-1.19.0.dist-info/WHEEL
pynmea2-1.19.0.dist-info/top_level.txt
pynmea2-1.19.0.dist-info/RECORD
